pi_spm/__init__.py
Python_SPM-1.1.dist-info/LICENSE.txt
Python_SPM-1.1.dist-info/METADATA
Python_SPM-1.1.dist-info/WHEEL
Python_SPM-1.1.dist-info/top_level.txt
Python_SPM-1.1.dist-info/RECORD
