Metadata-Version: 2.1
Name: Python-SPM
Version: 1.1
Summary: Python SPM is a Python wrapper for Pickering Switch Path Manager.
Home-page: 
Author: Pickering Interfaces
Author-email: Pickering Interfaces <support@pickeringtest.com>
License: Copyright (c) 2017-2023 Pickering Interfaces Ltd.
Project-URL: homepage, https://www.pickeringtest.com/
License-File: LICENSE.txt
Requires-Dist: future
